toru_vault/__init__.py
toru_vault/__main__.py
toru_vault/in_env.py
toru_vault/in_memory.py
toru_vault/lazy_dict.py
toru_vault/py.typed
toru_vault/vault.py
toru_vault-0.3.1.dist-info/licenses/LICENSE
toru_vault-0.3.1.dist-info/METADATA
toru_vault-0.3.1.dist-info/WHEEL
toru_vault-0.3.1.dist-info/entry_points.txt
toru_vault-0.3.1.dist-info/top_level.txt
toru_vault-0.3.1.dist-info/RECORD
