Metadata-Version: 2.4
Name: toru-vault
Version: 0.3.1
Summary: ToruVault: A simple Python package for managing Bitwarden secrets
Author: Toru AI
Author-email: ToruAI <mpaszynski@toruai.com>
License: MIT
Project-URL: Homepage, https://github.com/ToruAI/ToruVault
Project-URL: Issues, https://github.com/ToruAI/ToruVault/issues
Keywords: env manager,api key manager,secrets manager python,bitwarden python,environment variable manager,secret management,keyring,Bitwarden integration
Classifier: Programming Language :: Python :: 3
Classifier: License :: OSI Approved :: MIT License
Classifier: Operating System :: OS Independent
Classifier: Topic :: Security
Classifier: Topic :: Software Development :: Libraries :: Python Modules
Classifier: Intended Audience :: Developers
Classifier: Environment :: Console
Classifier: Topic :: System :: Systems Administration
Classifier: Topic :: Utilities
Requires-Python: >=3.6
License-File: LICENSE
Requires-Dist: bitwarden-sdk
Requires-Dist: cryptography>=36.0.0
Provides-Extra: keyring
Requires-Dist: keyring>=23.0.0; extra == "keyring"
Dynamic: author
Dynamic: license-file
Dynamic: requires-python
